Orange3_Survival_Analysis-0.6.3-py3.11-nspkg.pth
orange3_survival_analysis-0.6.3.dist-info/licenses/LICENSE
orangecontrib/survival_analysis/__init__.py
orangecontrib/survival_analysis/evaluation/__init__.py
orangecontrib/survival_analysis/evaluation/scoring.py
orangecontrib/survival_analysis/modeling/__init__.py
orangecontrib/survival_analysis/modeling/cox.py
orangecontrib/survival_analysis/tests/__init__.py
orangecontrib/survival_analysis/widgets/__init__.py
orangecontrib/survival_analysis/widgets/data.py
orangecontrib/survival_analysis/widgets/owassurvivaldata.py
orangecontrib/survival_analysis/widgets/owchorts.py
orangecontrib/survival_analysis/widgets/owcoxregression.py
orangecontrib/survival_analysis/widgets/owkaplanmeier.py
orangecontrib/survival_analysis/widgets/owranksurvivalfeatures.py
orangecontrib/survival_analysis/widgets/owstepwisecoxregression.py
orangecontrib/survival_analysis/widgets/owsurvivalnomogram.py
orangecontrib/survival_analysis/widgets/icons/category.svg
orangecontrib/survival_analysis/widgets/icons/owassurvivaldata.svg
orangecontrib/survival_analysis/widgets/icons/owcohorts.svg
orangecontrib/survival_analysis/widgets/icons/owcoxregression.svg
orangecontrib/survival_analysis/widgets/icons/owkaplanmeier.svg
orangecontrib/survival_analysis/widgets/icons/owranksurvivalfeatures.svg
orangecontrib/survival_analysis/widgets/icons/owstepwisecoxregression.svg
orangecontrib/survival_analysis/widgets/icons/owsurvivalnomogram.svg
orangecontrib/survival_analysis/widgets/tests/__init__.py
orangecontrib/survival_analysis/widgets/tests/test_owassurvivaldata.py
orangecontrib/survival_analysis/widgets/tests/test_owkaplanmeier.py
orangecontrib/survival_analysis/widgets/tests/test_owsurvivalnomogram.py
orangecontrib/survival_analysis/widgets/tests/datasets/README.txt
orangecontrib/survival_analysis/widgets/tests/datasets/melanoma.tab
orangecontrib/survival_analysis/widgets/tests/datasets/toy_example.tab
orange3_survival_analysis-0.6.3.dist-info/METADATA
orange3_survival_analysis-0.6.3.dist-info/WHEEL
orange3_survival_analysis-0.6.3.dist-info/entry_points.txt
orange3_survival_analysis-0.6.3.dist-info/namespace_packages.txt
orange3_survival_analysis-0.6.3.dist-info/top_level.txt
orange3_survival_analysis-0.6.3.dist-info/RECORD
