Metadata-Version: 2.4
Name: Orange3-Survival-Analysis
Version: 0.6.3
Summary: Survival Analysis add-on for Orange data mining software package.
Home-page: https://github.com/biolab/orange3-survival-analysis
Author: Bioinformatics Laboratory, FRI UL
Author-email: info@biolab.si
Maintainer: Jaka Kokosar
License: GPL3+
Project-URL: Bug Tracker, https://github.com/biolab/orange3-survival-analysis/issues
Project-URL: Source Code, https://github.com/biolab/orange3-survival-analysis/
Keywords: 'orange3 add-on'
Requires-Python: >=3.9
License-File: LICENSE
Requires-Dist: Orange3>=3.34.0
Requires-Dist: lifelines
Requires-Dist: statsmodels
Provides-Extra: doc
Requires-Dist: sphinx; extra == "doc"
Requires-Dist: recommonmark; extra == "doc"
Requires-Dist: sphinx_rtd_theme; extra == "doc"
Provides-Extra: test
Requires-Dist: pytest; extra == "test"
Requires-Dist: coverage; extra == "test"
Requires-Dist: flake8; extra == "test"
Requires-Dist: flake8-bugbear; extra == "test"
Requires-Dist: black; extra == "test"
Dynamic: license-file
